make_var/__init__.py
make_var/make_var.py
make_var-0.4.0.dist-info/LICENCE.txt
make_var-0.4.0.dist-info/METADATA
make_var-0.4.0.dist-info/WHEEL
make_var-0.4.0.dist-info/top_level.txt
make_var-0.4.0.dist-info/RECORD
