Metadata-Version: 2.1
Name: make-var
Version: 0.4.0
Summary: Retrieve all variables defined by make command
Home-page: http://github.com/karnigen/make_var
Author: Tony Karnigen
Author-email: karnigen@gmail.com
License: LICENSE.txt
Platform: any
Classifier: Programming Language :: Python :: 3
Classifier: License :: OSI Approved :: MIT License
Classifier: Operating System :: OS Independent
License-File: LICENCE.txt
